Workbook

Sheet Data_BudgetActual
A1: Month | B1: MonthNum | C1: Product Line | D1: Budget Revenue (BDT '000) | E1: Actual Revenue (BDT '000) | F1: Budget COGS (BDT '000) | G1: Actual COGS (BDT '000) | H1: Budget GP (BDT '000) | I1: Actual GP (BDT '000) | J1: Rev Variance (BDT '000) | K1: Rev Variance % | L1: GP Variance (BDT '000) | M1: GP Variance %
A2: Jul-24 | B2: 1 | C2: Foil Laminate | D2: 32062 | E2: 33187 | F2: 21802 | G2: 21962 | H2: =D2-F2 -> 10260 | I2: =E2-G2 -> 11225 | J2: =E2-D2 -> 1125 | K2: =IFERROR(J2/D2,0) -> 0.035088266 | L2: =I2-H2 -> 965 | M2: =IFERROR(L2/H2,0) -> 0.094054581
A3: Jul-24 | B3: 1 | C3: Film Laminate | D3: 24938 | E3: 24178 | F3: 16958 | G3: 16335 | H3: =D3-F3 -> 7980 | I3: =E3-G3 -> 7843 | J3: =E3-D3 -> -760 | K3: =IFERROR(J3/D3,0) -> -0.030475579 | L3: =I3-H3 -> -137 | M3: =IFERROR(L3/H3,0) -> -0.01716792
A4: Jul-24 | B4: 1 | C4: Paper Laminate | D4: 14250 | E4: 14999 | F4: 9690 | G4: 10610 | H4: =D4-F4 -> 4560 | I4: =E4-G4 -> 4389 | J4: =E4-D4 -> 749 | K4: =IFERROR(J4/D4,0) -> 0.052561404 | L4: =I4-H4 -> -171 | M4: =IFERROR(L4/H4,0) -> -0.0375
A5: Aug-24 | B5: 2 | C5: Foil Laminate | D5: 30281 | E5: 32721 | F5: 20591 | G5: 21795 | H5: =D5-F5 -> 9690 | I5: =E5-G5 -> 10926 | J5: =E5-D5 -> 2440 | K5: =IFERROR(J5/D5,0) -> 0.080578581 | L5: =I5-H5 -> 1236 | M5: =IFERROR(L5/H5,0) -> 0.12755418
A6: Aug-24 | B6: 2 | C6: Film Laminate | D6: 23552 | E6: 23457 | F6: 16015 | G6: 15531 | H6: =D6-F6 -> 7537 | I6: =E6-G6 -> 7926 | J6: =E6-D6 -> -95 | K6: =IFERROR(J6/D6,0) -> -0.0040336277 | L6: =I6-H6 -> 389 | M6: =IFERROR(L6/H6,0) -> 0.051612047
A7: Aug-24 | B7: 2 | C7: Paper Laminate | D7: 13458 | E7: 12911 | F7: 9151 | G7: 8978 | H7: =D7-F7 -> 4307 | I7: =E7-G7 -> 3933 | J7: =E7-D7 -> -547 | K7: =IFERROR(J7/D7,0) -> -0.04064497 | L7: =I7-H7 -> -374 | M7: =IFERROR(L7/H7,0) -> -0.086835384
A8: Sep-24 | B8: 3 | C8: Foil Laminate | D8: 33844 | E8: 31298 | F8: 23014 | G8: 21092 | H8: =D8-F8 -> 10830 | I8: =E8-G8 -> 10206 | J8: =E8-D8 -> -2546 | K8: =IFERROR(J8/D8,0) -> -0.075227514 | L8: =I8-H8 -> -624 | M8: =IFERROR(L8/H8,0) -> -0.057617729
A9: Sep-24 | B9: 3 | C9: Film Laminate | D9: 26323 | E9: 27296 | F9: 17900 | G9: 19057 | H9: =D9-F9 -> 8423 | I9: =E9-G9 -> 8239 | J9: =E9-D9 -> 973 | K9: =IFERROR(J9/D9,0) -> 0.036963872 | L9: =I9-H9 -> -184 | M9: =IFERROR(L9/H9,0) -> -0.021844948
A10: Sep-24 | B10: 3 | C10: Paper Laminate | D10: 15042 | E10: 14435 | F10: 10229 | G10: 10123 | H10: =D10-F10 -> 4813 | I10: =E10-G10 -> 4312 | J10: =E10-D10 -> -607 | K10: =IFERROR(J10/D10,0) -> -0.040353676 | L10: =I10-H10 -> -501 | M10: =IFERROR(L10/H10,0) -> -0.10409308
A11: Oct-24 | B11: 4 | C11: Foil Laminate | D11: 40969 | E11: 43661 | F11: 27859 | G11: 28836 | H11: =D11-F11 -> 13110 | I11: =E11-G11 -> 14825 | J11: =E11-D11 -> 2692 | K11: =IFERROR(J11/D11,0) -> 0.065708218 | L11: =I11-H11 -> 1715 | M11: =IFERROR(L11/H11,0) -> 0.13081617
A12: Oct-24 | B12: 4 | C12: Film Laminate | D12: 31865 | E12: 33938 | F12: 21668 | G12: 24058 | H12: =D12-F12 -> 10197 | I12: =E12-G12 -> 9880 | J12: =E12-D12 -> 2073 | K12: =IFERROR(J12/D12,0) -> 0.065055704 | L12: =I12-H12 -> -317 | M12: =IFERROR(L12/H12,0) -> -0.031087575
A13: Oct-24 | B13: 4 | C13: Paper Laminate | D13: 18208 | E13: 17867 | F13: 12381 | G13: 11987 | H13: =D13-F13 -> 5827 | I13: =E13-G13 -> 5880 | J13: =E13-D13 -> -341 | K13: =IFERROR(J13/D13,0) -> -0.018728032 | L13: =I13-H13 -> 53 | M13: =IFERROR(L13/H13,0) -> 0.0090955895
... A37: Jun-25 | B37: 12 | C37: Paper Laminate | D37: 15042 | E37: 14410 | F37: 10229 | G37: 10462 | H37: =D37-F37 -> 4813 | I37: =E37-G37 -> 3948 | J37: =E37-D37 -> -632 | K37: =IFERROR(J37/D37,0) -> -0.042015689 | L37: =I37-H37 -> -865 | M37: =IFERROR(L37/H37,0) -> -0.17972159
A39: Note: illustrative monthly data built to a realistic flexible-packaging cost/margin profile for interview demonstration; see 'Assumptions & Sources' tab.

Sheet MBR_Dashboard
A1: Premiaflex Plastics Limited (Illustrative) — Monthly Business Review Dashboard
A2: FY 2024–25 | Budget vs. Actual | Prepared for Business Planning interview demonstration
A4: YTD Actual Revenue (BDT '000) | D4: YTD Budget Revenue (BDT '000) | G4: Revenue Variance % | J4: YTD Actual GP Margin % | M4: YTD Budget GP Margin %
A5: =SUM(Data_BudgetActual!E2:E37) -> 964588 | D5: =SUM(Data_BudgetActual!D2:D37) -> 950002 | G5: =(A5-D5)/D5 -> 0.015353652 | J5: =SUM(Data_BudgetActual!I2:I37)/SUM(Data_BudgetActual!E2:E37) -> 0.31078865 | M5: =SUM(Data_BudgetActual!H2:H37)/SUM(Data_BudgetActual!D2:D37) -> 0.31999933
A8: Monthly Summary (all product lines)
A9: Month | B9: MonthNum | C9: Budget Revenue | D9: Actual Revenue | E9: Rev Variance | F9: Rev Var % | G9: Budget GP | H9: Actual GP | I9: GP Variance | J9: Actual GP Margin % | K9: Budget GP Margin %
A10: Jul-24 | B10: 1 | C10: =SUMIFS(Data_BudgetActual!$D$2:$D$37,Data_BudgetActual!$A$2:$A$37,A10) -> 71250 | D10: =SUMIFS(Data_BudgetActual!$E$2:$E$37,Data_BudgetActual!$A$2:$A$37,A10) -> 72364 | E10: =D10-C10 -> 1114 | F10: =IFERROR(E10/C10,0) -> 0.015635088 | G10: =SUMIFS(Data_BudgetActual!$H$2:$H$37,Data_BudgetActual!$A$2:$A$37,A10) -> 22800 | H10: =SUMIFS(Data_BudgetActual!$I$2:$I$37,Data_BudgetActual!$A$2:$A$37,A10) -> 23457 | I10: =H10-G10 -> 657 | J10: =IFERROR(H10/D10,0) -> 0.32415289 | K10: =IFERROR(G10/C10,0) -> 0.32
A11: Aug-24 | B11: 2 | C11: =SUMIFS(Data_BudgetActual!$D$2:$D$37,Data_BudgetActual!$A$2:$A$37,A11) -> 67291 | D11: =SUMIFS(Data_BudgetActual!$E$2:$E$37,Data_BudgetActual!$A$2:$A$37,A11) -> 69089 | E11: =D11-C11 -> 1798 | F11: =IFERROR(E11/C11,0) -> 0.026719769 | G11: =SUMIFS(Data_BudgetActual!$H$2:$H$37,Data_BudgetActual!$A$2:$A$37,A11) -> 21534 | H11: =SUMIFS(Data_BudgetActual!$I$2:$I$37,Data_BudgetActual!$A$2:$A$37,A11) -> 22785 | I11: =H11-G11 -> 1251 | J11: =IFERROR(H11/D11,0) -> 0.32979201 | K11: =IFERROR(G11/C11,0) -> 0.32001308
A12: Sep-24 | B12: 3 | C12: =SUMIFS(Data_BudgetActual!$D$2:$D$37,Data_BudgetActual!$A$2:$A$37,A12) -> 75209 | D12: =SUMIFS(Data_BudgetActual!$E$2:$E$37,Data_BudgetActual!$A$2:$A$37,A12) -> 73029 | E12: =D12-C12 -> -2180 | F12: =IFERROR(E12/C12,0) -> -0.028985893 | G12: =SUMIFS(Data_BudgetActual!$H$2:$H$37,Data_BudgetActual!$A$2:$A$37,A12) -> 24066 | H12: =SUMIFS(Data_BudgetActual!$I$2:$I$37,Data_BudgetActual!$A$2:$A$37,A12) -> 22757 | I12: =H12-G12 -> -1309 | J12: =IFERROR(H12/D12,0) -> 0.31161593 | K12: =IFERROR(G12/C12,0) -> 0.3199883
A13: Oct-24 | B13: 4 | C13: =SUMIFS(Data_BudgetActual!$D$2:$D$37,Data_BudgetActual!$A$2:$A$37,A13) -> 91042 | D13: =SUMIFS(Data_BudgetActual!$E$2:$E$37,Data_BudgetActual!$A$2:$A$37,A13) -> 95466 | E13: =D13-C13 -> 4424 | F13: =IFERROR(E13/C13,0) -> 0.048592957 | G13: =SUMIFS(Data_BudgetActual!$H$2:$H$37,Data_BudgetActual!$A$2:$A$37,A13) -> 29134 | H13: =SUMIFS(Data_BudgetActual!$I$2:$I$37,Data_BudgetActual!$A$2:$A$37,A13) -> 30585 | I13: =H13-G13 -> 1451 | J13: =IFERROR(H13/D13,0) -> 0.32037584 | K13: =IFERROR(G13/C13,0) -> 0.32000615
A14: Nov-24 | B14: 5 | C14: =SUMIFS(Data_BudgetActual!$D$2:$D$37,Data_BudgetActual!$A$2:$A$37,A14) -> 95000 | D14: =SUMIFS(Data_BudgetActual!$E$2:$E$37,Data_BudgetActual!$A$2:$A$37,A14) -> 98219 | E14: =D14-C14 -> 3219 | F14: =IFERROR(E14/C14,0) -> 0.033884211 | G14: =SUMIFS(Data_BudgetActual!$H$2:$H$37,Data_BudgetActual!$A$2:$A$37,A14) -> 30400 | H14: =SUMIFS(Data_BudgetActual!$I$2:$I$37,Data_BudgetActual!$A$2:$A$37,A14) -> 31221 | I14: =H14-G14 -> 821 | J14: =IFERROR(H14/D14,0) -> 0.31787129 | K14: =IFERROR(G14/C14,0) -> 0.32
A15: Dec-24 | B15: 6 | C15: =SUMIFS(Data_BudgetActual!$D$2:$D$37,Data_BudgetActual!$A$2:$A$37,A15) -> 91042 | D15: =SUMIFS(Data_BudgetActual!$E$2:$E$37,Data_BudgetActual!$A$2:$A$37,A15) -> 94027 | E15: =D15-C15 -> 2985 | F15: =IFERROR(E15/C15,0) -> 0.032787065 | G15: =SUMIFS(Data_BudgetActual!$H$2:$H$37,Data_BudgetActual!$A$2:$A$37,A15) -> 29134 | H15: =SUMIFS(Data_BudgetActual!$I$2:$I$37,Data_BudgetActual!$A$2:$A$37,A15) -> 26839 | I15: =H15-G15 -> -2295 | J15: =IFERROR(H15/D15,0) -> 0.28543929 | K15: =IFERROR(G15/C15,0) -> 0.32000615
A16: Jan-25 | B16: 7 | C16: =SUMIFS(Data_BudgetActual!$D$2:$D$37,Data_BudgetActual!$A$2:$A$37,A16) -> 79166 | D16: =SUMIFS(Data_BudgetActual!$E$2:$E$37,Data_BudgetActual!$A$2:$A$37,A16) -> 84457 | E16: =D16-C16 -> 5291 | F16: =IFERROR(E16/C16,0) -> 0.066834247 | G16: =SUMIFS(Data_BudgetActual!$H$2:$H$37,Data_BudgetActual!$A$2:$A$37,A16) -> 25334 | H16: =SUMIFS(Data_BudgetActual!$I$2:$I$37,Data_BudgetActual!$A$2:$A$37,A16) -> 25809 | I16: =H16-G16 -> 475 | J16: =IFERROR(H16/D16,0) -> 0.30558746 | K16: =IFERROR(G16/C16,0) -> 0.32001112
A17: Feb-25 | B17: 8 | C17: =SUMIFS(Data_BudgetActual!$D$2:$D$37,Data_BudgetActual!$A$2:$A$37,A17) -> 75209 | D17: =SUMIFS(Data_BudgetActual!$E$2:$E$37,Data_BudgetActual!$A$2:$A$37,A17) -> 71232 | E17: =D17-C17 -> -3977 | F17: =IFERROR(E17/C17,0) -> -0.05287931 | G17: =SUMIFS(Data_BudgetActual!$H$2:$H$37,Data_BudgetActual!$A$2:$A$37,A17) -> 24066 | H17: =SUMIFS(Data_BudgetActual!$I$2:$I$37,Data_BudgetActual!$A$2:$A$37,A17) -> 22885 | I17: =H17-G17 -> -1181 | J17: =IFERROR(H17/D17,0) -> 0.32127415 | K17: =IFERROR(G17/C17,0) -> 0.3199883
A18: Mar-25 | B18: 9 | C18: =SUMIFS(Data_BudgetActual!$D$2:$D$37,Data_BudgetActual!$A$2:$A$37,A18) -> 79166 | D18: =SUMIFS(Data_BudgetActual!$E$2:$E$37,Data_BudgetActual!$A$2:$A$37,A18) -> 79516 | E18: =D18-C18 -> 350 | F18: =IFERROR(E18/C18,0) -> 0.0044210899 | G18: =SUMIFS(Data_BudgetActual!$H$2:$H$37,Data_BudgetActual!$A$2:$A$37,A18) -> 25334 | H18: =SUMIFS(Data_BudgetActual!$I$2:$I$37,Data_BudgetActual!$A$2:$A$37,A18) -> 24688 | I18: =H18-G18 -> -646 | J18: =IFERROR(H18/D18,0) -> 0.31047839 | K18: =IFERROR(G18/C18,0) -> 0.32001112
A19: Apr-25 | B19: 10 | C19: =SUMIFS(Data_BudgetActual!$D$2:$D$37,Data_BudgetActual!$A$2:$A$37,A19) -> 75209 | D19: =SUMIFS(Data_BudgetActual!$E$2:$E$37,Data_BudgetActual!$A$2:$A$37,A19) -> 74393 | E19: =D19-C19 -> -816 | F19: =IFERROR(E19/C19,0) -> -0.010849765 | G19: =SUMIFS(Data_BudgetActual!$H$2:$H$37,Data_BudgetActual!$A$2:$A$37,A19) -> 24066 | H19: =SUMIFS(Data_BudgetActual!$I$2:$I$37,Data_BudgetActual!$A$2:$A$37,A19) -> 22141 | I19: =H19-G19 -> -1925 | J19: =IFERROR(H19/D19,0) -> 0.29762209 | K19: =IFERROR(G19/C19,0) -> 0.3199883
A20: May-25 | B20: 11 | C20: =SUMIFS(Data_BudgetActual!$D$2:$D$37,Data_BudgetActual!$A$2:$A$37,A20) -> 75209 | D20: =SUMIFS(Data_BudgetActual!$E$2:$E$37,Data_BudgetActual!$A$2:$A$37,A20) -> 80142 | E20: =D20-C20 -> 4933 | F20: =IFERROR(E20/C20,0) -> 0.065590554 | G20: =SUMIFS(Data_BudgetActual!$H$2:$H$37,Data_BudgetActual!$A$2:$A$37,A20) -> 24066 | H20: =SUMIFS(Data_BudgetActual!$I$2:$I$37,Data_BudgetActual!$A$2:$A$37,A20) -> 23420 | I20: =H20-G20 -> -646 | J20: =IFERROR(H20/D20,0) -> 0.29223129 | K20: =IFERROR(G20/C20,0) -> 0.3199883
A21: Jun-25 | B21: 12 | C21: =SUMIFS(Data_BudgetActual!$D$2:$D$37,Data_BudgetActual!$A$2:$A$37,A21) -> 75209 | D21: =SUMIFS(Data_BudgetActual!$E$2:$E$37,Data_BudgetActual!$A$2:$A$37,A21) -> 72654 | E21: =D21-C21 -> -2555 | F21: =IFERROR(E21/C21,0) -> -0.033971998 | G21: =SUMIFS(Data_BudgetActual!$H$2:$H$37,Data_BudgetActual!$A$2:$A$37,A21) -> 24066 | H21: =SUMIFS(Data_BudgetActual!$I$2:$I$37,Data_BudgetActual!$A$2:$A$37,A21) -> 23196 | I21: =H21-G21 -> -870 | J21: =IFERROR(H21/D21,0) -> 0.31926666 | K21: =IFERROR(G21/C21,0) -> 0.3199883

Sheet Variance_Analysis
A1: Annual Cost Variance Analysis (FY 2024–25)
A2: Budget vs. Actual by cost category, with variance drivers for MBR discussion
A4: Total Budget Revenue (BDT '000) | B4: =SUM(Data_BudgetActual!D2:D37) -> 950002
A5: Total Actual Revenue (BDT '000) | B5: =SUM(Data_BudgetActual!E2:E37) -> 964588
A6: Total Budget COGS (BDT '000) | B6: =SUM(Data_BudgetActual!F2:F37) -> 646002
A7: Total Actual COGS (BDT '000) | B7: =SUM(Data_BudgetActual!G2:G37) -> 664805
A10: Cost Category | B10: Budget (BDT '000) | C10: Actual (BDT '000) | D10: Variance (BDT '000) | E10: Variance % | F10: Driver Commentary
A11: Raw Materials (Resin / Foil / Ink) | B11: =$B$6*0.68 -> 439281.36 | C11: =$B$7*0.71 -> 472011.55 | D11: =C11-B11 -> 32730.19 | E11: =IFERROR(D11/B11,0) -> 0.074508488 | F11: Unfavorable — global resin & aluminium foil prices rose faster than the budgeted rate; partly offset by better wastage control.
A12: Direct Labor | B12: =$B$6*0.12 -> 77520.24 | C12: =$B$7*0.115 -> 76452.575 | D12: =C12-B12 -> -1067.665 | E12: =IFERROR(D12/B12,0) -> -0.013772726 | F12: Favorable — improved shift utilization on the new Flexo CI line reduced overtime.
A13: Manufacturing Overhead (Power, Maintenance) | B13: =$B$6*0.2 -> 129200.4 | C13: =$B$7*0.205 -> 136285.02 | D13: =C13-B13 -> 7084.625 | E13: =IFERROR(D13/B13,0) -> 0.054834389 | F13: Broadly on budget — a planned maintenance shutdown in Nov-24 offset lower grid tariffs.
A14: Distribution & Freight | B14: =$B$4*0.045 -> 42750.09 | C14: =$B$5*0.052 -> 50158.576 | D14: =C14-B14 -> 7408.486 | E14: =IFERROR(D14/B14,0) -> 0.17329755 | F14: Unfavorable — higher fuel surcharges and a shift toward smaller, more frequent MNC deliveries.
A15: Selling & Admin Expenses | B15: =$B$4*0.075 -> 71250.15 | C15: =$B$5*0.07 -> 67521.16 | D15: =C15-B15 -> -3728.99 | E15: =IFERROR(D15/B15,0) -> -0.052336592 | F15: Favorable — admin cost discipline and lower travel spend versus plan.
A16: Total Cost Base | B16: =SUM(B11:B15) -> 760002.24 | C16: =SUM(C11:C15) -> 802428.89 | D16: =C16-B16 -> 42426.646 | E16: =IFERROR(D16/B16,0) -> 0.05582437

Sheet Profitability_Analysis
A1: Product-wise and Customer-wise Profitability Analysis (FY 2024–25 Actuals)
A3: 1. Product-wise Profitability
A4: Product Line | B4: Revenue (BDT '000) | C4: Variable Cost (BDT '000) | D4: Contribution Margin (BDT '000) | E4: CM % | F4: Allocated Fixed OH (BDT '000) | G4: Net Profit (BDT '000) | H4: Net Margin %
A5: Foil Laminate | B5: =SUMIFS(Data_BudgetActual!$E$2:$E$37,Data_BudgetActual!$C$2:$C$37,A5) -> 443458 | C5: =SUMIFS(Data_BudgetActual!$G$2:$G$37,Data_BudgetActual!$C$2:$C$37,A5) -> 303207 | D5: =B5-C5 -> 140251 | E5: =IFERROR(D5/B5,0) -> 0.3162667 | F5: =(Variance_Analysis!$C$14+Variance_Analysis!$C$15)*B5/Profitability_Analysis!$B$8 -> 54101.876 | G5: =D5-F5 -> 86149.124 | H5: =IFERROR(G5/B5,0) -> 0.1942667
A6: Film Laminate | B6: =SUMIFS(Data_BudgetActual!$E$2:$E$37,Data_BudgetActual!$C$2:$C$37,A6) -> 331723 | C6: =SUMIFS(Data_BudgetActual!$G$2:$G$37,Data_BudgetActual!$C$2:$C$37,A6) -> 229534 | D6: =B6-C6 -> 102189 | E6: =IFERROR(D6/B6,0) -> 0.30805521 | F6: =(Variance_Analysis!$C$14+Variance_Analysis!$C$15)*B6/Profitability_Analysis!$B$8 -> 40470.206 | G6: =D6-F6 -> 61718.794 | H6: =IFERROR(G6/B6,0) -> 0.18605521
A7: Paper Laminate | B7: =SUMIFS(Data_BudgetActual!$E$2:$E$37,Data_BudgetActual!$C$2:$C$37,A7) -> 189407 | C7: =SUMIFS(Data_BudgetActual!$G$2:$G$37,Data_BudgetActual!$C$2:$C$37,A7) -> 132064 | D7: =B7-C7 -> 57343 | E7: =IFERROR(D7/B7,0) -> 0.30275016 | F7: =(Variance_Analysis!$C$14+Variance_Analysis!$C$15)*B7/Profitability_Analysis!$B$8 -> 23107.654 | G7: =D7-F7 -> 34235.346 | H7: =IFERROR(G7/B7,0) -> 0.18075016
A8: Total | B8: =SUM(B5:B7) -> 964588 | C8: =SUM(C5:C7) -> 664805 | D8: =SUM(D5:D7) -> 299783 | E8: =IFERROR(D8/B8,0) -> 0.31078865 | F8: =SUM(F5:F7) -> 117679.74 | G8: =SUM(G5:G7) -> 182103.26 | H8: =IFERROR(G8/B8,0) -> 0.18878865
A28: 2. Customer-wise Profitability
A29: Customer | B29: Revenue Share % | C29: Revenue (BDT '000) | D29: Contribution Margin % | E29: Contribution Margin (BDT '000)
A30: Unilever | B30: 0.28 | C30: =B30*$B$8 -> 270084.64 | D30: 0.34 | E30: =C30*D30 -> 91828.778
A31: Marico | B31: 0.18 | C31: =B31*$B$8 -> 173625.84 | D31: 0.36 | E31: =C31*D31 -> 62505.302
A32: Emami | B32: 0.12 | C32: =B32*$B$8 -> 115750.56 | D32: 0.33 | E32: =C32*D32 -> 38197.685
A33: Coca-Cola | B33: 0.15 | C33: =B33*$B$8 -> 144688.2 | D33: 0.3 | E33: =C33*D33 -> 43406.46
A34: British American Tobacco (BAT) | B34: 0.17 | C34: =B34*$B$8 -> 163979.96 | D34: 0.38 | E34: =C34*D34 -> 62312.385
A35: Other B2B Customers | B35: 0.1 | C35: =B35*$B$8 -> 96458.8 | D35: 0.28 | E35: =C35*D35 -> 27008.464
A36: Total | B36: =SUM(B30:B35) -> 1 | C36: =SUM(C30:C35) -> 964588 | E36: =SUM(E30:E35) -> 325259.07

Sheet Working_Capital_CashFlow
A1: Working Capital & Cash Conversion Cycle (FY 2024–25, Monthly)
A3: Target Days on Hand (edit blue cells):
A4: DIO (Inventory days) | B4: 45
A5: DSO (Receivable days) | B5: 55
A6: DPO (Payable days) | B6: 40
A8: Month | B8: Actual Revenue | C8: Actual COGS | D8: Inventory | E8: Receivables | F8: Payables | G8: Net Working Capital | H8: DIO (days) | I8: DSO (days) | J8: CCC (days)
A9: Jul-24 | B9: =SUMIFS(Data_BudgetActual!$E$2:$E$37,Data_BudgetActual!$A$2:$A$37,A9) -> 72364 | C9: =SUMIFS(Data_BudgetActual!$G$2:$G$37,Data_BudgetActual!$A$2:$A$37,A9) -> 48907 | D9: =$B$4/365*C9*12 -> 72355.562 | E9: =$B$5/365*B9*12 -> 130849.97 | F9: =$B$6/365*C9*12 -> 64316.055 | G9: =D9+E9-F9 -> 138889.48 | H9: =$B$4 -> 45 | I9: =$B$5 -> 55 | J9: =H9+I9-$B$6 -> 60
A10: Aug-24 | B10: =SUMIFS(Data_BudgetActual!$E$2:$E$37,Data_BudgetActual!$A$2:$A$37,A10) -> 69089 | C10: =SUMIFS(Data_BudgetActual!$G$2:$G$37,Data_BudgetActual!$A$2:$A$37,A10) -> 46304 | D10: =$B$4/365*C10*12 -> 68504.548 | E10: =$B$5/365*B10*12 -> 124928.05 | F10: =$B$6/365*C10*12 -> 60892.932 | G10: =D10+E10-F10 -> 132539.67 | H10: =$B$4 -> 45 | I10: =$B$5 -> 55 | J10: =H10+I10-$B$6 -> 60
A11: Sep-24 | B11: =SUMIFS(Data_BudgetActual!$E$2:$E$37,Data_BudgetActual!$A$2:$A$37,A11) -> 73029 | C11: =SUMIFS(Data_BudgetActual!$G$2:$G$37,Data_BudgetActual!$A$2:$A$37,A11) -> 50272 | D11: =$B$4/365*C11*12 -> 74375.014 | E11: =$B$5/365*B11*12 -> 132052.44 | F11: =$B$6/365*C11*12 -> 66111.123 | G11: =D11+E11-F11 -> 140316.33 | H11: =$B$4 -> 45 | I11: =$B$5 -> 55 | J11: =H11+I11-$B$6 -> 60
A12: Oct-24 | B12: =SUMIFS(Data_BudgetActual!$E$2:$E$37,Data_BudgetActual!$A$2:$A$37,A12) -> 95466 | C12: =SUMIFS(Data_BudgetActual!$G$2:$G$37,Data_BudgetActual!$A$2:$A$37,A12) -> 64881 | D12: =$B$4/365*C12*12 -> 95988.329 | E12: =$B$5/365*B12*12 -> 172623.45 | F12: =$B$6/365*C12*12 -> 85322.959 | G12: =D12+E12-F12 -> 183288.82 | H12: =$B$4 -> 45 | I12: =$B$5 -> 55 | J12: =H12+I12-$B$6 -> 60
A13: Nov-24 | B13: =SUMIFS(Data_BudgetActual!$E$2:$E$37,Data_BudgetActual!$A$2:$A$37,A13) -> 98219 | C13: =SUMIFS(Data_BudgetActual!$G$2:$G$37,Data_BudgetActual!$A$2:$A$37,A13) -> 66998 | D13: =$B$4/365*C13*12 -> 99120.329 | E13: =$B$5/365*B13*12 -> 177601.48 | F13: =$B$6/365*C13*12 -> 88106.959 | G13: =D13+E13-F13 -> 188614.85 | H13: =$B$4 -> 45 | I13: =$B$5 -> 55 | J13: =H13+I13-$B$6 -> 60
A14: Dec-24 | B14: =SUMIFS(Data_BudgetActual!$E$2:$E$37,Data_BudgetActual!$A$2:$A$37,A14) -> 94027 | C14: =SUMIFS(Data_BudgetActual!$G$2:$G$37,Data_BudgetActual!$A$2:$A$37,A14) -> 67188 | D14: =$B$4/365*C14*12 -> 99401.425 | E14: =$B$5/365*B14*12 -> 170021.42 | F14: =$B$6/365*C14*12 -> 88356.822 | G14: =D14+E14-F14 -> 181066.03 | H14: =$B$4 -> 45 | I14: =$B$5 -> 55 | J14: =H14+I14-$B$6 -> 60
A15: Jan-25 | B15: =SUMIFS(Data_BudgetActual!$E$2:$E$37,Data_BudgetActual!$A$2:$A$37,A15) -> 84457 | C15: =SUMIFS(Data_BudgetActual!$G$2:$G$37,Data_BudgetActual!$A$2:$A$37,A15) -> 58648 | D15: =$B$4/365*C15*12 -> 86766.904 | E15: =$B$5/365*B15*12 -> 152716.77 | F15: =$B$6/365*C15*12 -> 77126.137 | G15: =D15+E15-F15 -> 162357.53 | H15: =$B$4 -> 45 | I15: =$B$5 -> 55 | J15: =H15+I15-$B$6 -> 60
A16: Feb-25 | B16: =SUMIFS(Data_BudgetActual!$E$2:$E$37,Data_BudgetActual!$A$2:$A$37,A16) -> 71232 | C16: =SUMIFS(Data_BudgetActual!$G$2:$G$37,Data_BudgetActual!$A$2:$A$37,A16) -> 48347 | D16: =$B$4/365*C16*12 -> 71527.068 | E16: =$B$5/365*B16*12 -> 128803.07 | F16: =$B$6/365*C16*12 -> 63579.616 | G16: =D16+E16-F16 -> 136750.52 | H16: =$B$4 -> 45 | I16: =$B$5 -> 55 | J16: =H16+I16-$B$6 -> 60
A17: Mar-25 | B17: =SUMIFS(Data_BudgetActual!$E$2:$E$37,Data_BudgetActual!$A$2:$A$37,A17) -> 79516 | C17: =SUMIFS(Data_BudgetActual!$G$2:$G$37,Data_BudgetActual!$A$2:$A$37,A17) -> 54828 | D17: =$B$4/365*C17*12 -> 81115.397 | E17: =$B$5/365*B17*12 -> 143782.36 | F17: =$B$6/365*C17*12 -> 72102.575 | G17: =D17+E17-F17 -> 152795.18 | H17: =$B$4 -> 45 | I17: =$B$5 -> 55 | J17: =H17+I17-$B$6 -> 60
A18: Apr-25 | B18: =SUMIFS(Data_BudgetActual!$E$2:$E$37,Data_BudgetActual!$A$2:$A$37,A18) -> 74393 | C18: =SUMIFS(Data_BudgetActual!$G$2:$G$37,Data_BudgetActual!$A$2:$A$37,A18) -> 52252 | D18: =$B$4/365*C18*12 -> 77304.329 | E18: =$B$5/365*B18*12 -> 134518.85 | F18: =$B$6/365*C18*12 -> 68714.959 | G18: =D18+E18-F18 -> 143108.22 | H18: =$B$4 -> 45 | I18: =$B$5 -> 55 | J18: =H18+I18-$B$6 -> 60
A19: May-25 | B19: =SUMIFS(Data_BudgetActual!$E$2:$E$37,Data_BudgetActual!$A$2:$A$37,A19) -> 80142 | C19: =SUMIFS(Data_BudgetActual!$G$2:$G$37,Data_BudgetActual!$A$2:$A$37,A19) -> 56722 | D19: =$B$4/365*C19*12 -> 83917.479 | E19: =$B$5/365*B19*12 -> 144914.3 | F19: =$B$6/365*C19*12 -> 74593.315 | G19: =D19+E19-F19 -> 154238.47 | H19: =$B$4 -> 45 | I19: =$B$5 -> 55 | J19: =H19+I19-$B$6 -> 60
A20: Jun-25 | B20: =SUMIFS(Data_BudgetActual!$E$2:$E$37,Data_BudgetActual!$A$2:$A$37,A20) -> 72654 | C20: =SUMIFS(Data_BudgetActual!$G$2:$G$37,Data_BudgetActual!$A$2:$A$37,A20) -> 49458 | D20: =$B$4/365*C20*12 -> 73170.74 | E20: =$B$5/365*B20*12 -> 131374.36 | F20: =$B$6/365*C20*12 -> 65040.658 | G20: =D20+E20-F20 -> 139504.44 | H20: =$B$4 -> 45 | I20: =$B$5 -> 55 | J20: =H20+I20-$B$6 -> 60
A22: FY Average | D22: =AVERAGE(D9:D20) -> 81962.26 | E22: =AVERAGE(E9:E20) -> 145348.88 | F22: =AVERAGE(F9:F20) -> 72855.342 | G22: =AVERAGE(G9:G20) -> 154455.79 | J22: =AVERAGE(J9:J20) -> 60

Sheet Feasibility_NewLine
A1: Financial Feasibility: New Lamination Line (Capacity Expansion)
A2: Illustrative scenario analysis for a management investment decision (interview demo)
A4: Key Assumptions
A5: Capital Investment (BDT '000) | B5: 120000
A6: Year 1 Incremental Revenue (BDT '000) | B6: 180000
A7: Annual Revenue Growth Rate | B7: 0.08
A8: Variable Cost % of Revenue | B8: 0.65
A9: Incremental Fixed OpEx (BDT '000/yr) | B9: 15000
A10: Project Life (years) | B10: 5
A11: Tax Rate | B11: 0.25
A12: Discount Rate (WACC) | B12: 0.12
A15: 5-Year Cash Flow Projection
A16: Line Item | B16: Year 0 | C16: Year 1 | D16: Year 2 | E16: Year 3 | F16: Year 4 | G16: Year 5
A17: Revenue | C17: =$B$6 -> 180000 | D17: =C17*(1+$B$7) -> 194400 | E17: =D17*(1+$B$7) -> 209952 | F17: =E17*(1+$B$7) -> 226748.16 | G17: =F17*(1+$B$7) -> 244888.01
A18: Variable Cost | C18: =C17*$B$8 -> 117000 | D18: =D17*$B$8 -> 126360 | E18: =E17*$B$8 -> 136468.8 | F18: =F17*$B$8 -> 147386.3 | G18: =G17*$B$8 -> 159177.21
A19: Contribution Margin | C19: =C17-C18 -> 63000 | D19: =D17-D18 -> 68040 | E19: =E17-E18 -> 73483.2 | F19: =F17-F18 -> 79361.856 | G19: =G17-G18 -> 85710.804
A20: Fixed OpEx | C20: =$B$9 -> 15000 | D20: =$B$9 -> 15000 | E20: =$B$9 -> 15000 | F20: =$B$9 -> 15000 | G20: =$B$9 -> 15000
A21: EBITDA | C21: =C19-C20 -> 48000 | D21: =D19-D20 -> 53040 | E21: =E19-E20 -> 58483.2 | F21: =F19-F20 -> 64361.856 | G21: =G19-G20 -> 70710.804
A22: Depreciation | C22: =$B$5/$B$10 -> 24000 | D22: =$B$5/$B$10 -> 24000 | E22: =$B$5/$B$10 -> 24000 | F22: =$B$5/$B$10 -> 24000 | G22: =$B$5/$B$10 -> 24000
A23: EBIT | C23: =C21-C22 -> 24000 | D23: =D21-D22 -> 29040 | E23: =E21-E22 -> 34483.2 | F23: =F21-F22 -> 40361.856 | G23: =G21-G22 -> 46710.804
A24: Tax | C24: =MAX(C23,0)*$B$11 -> 6000 | D24: =MAX(D23,0)*$B$11 -> 7260 | E24: =MAX(E23,0)*$B$11 -> 8620.8 | F24: =MAX(F23,0)*$B$11 -> 10090.464 | G24: =MAX(G23,0)*$B$11 -> 11677.701
A25: Net Income | C25: =C23-C24 -> 18000 | D25: =D23-D24 -> 21780 | E25: =E23-E24 -> 25862.4 | F25: =F23-F24 -> 30271.392 | G25: =G23-G24 -> 35033.103
A26: Net Cash Flow | B26: =-B5 -> -120000 | C26: =C25+C22 -> 42000 | D26: =D25+D22 -> 45780 | E26: =E25+E22 -> 49862.4 | F26: =F25+F22 -> 54271.392 | G26: =G25+G22 -> 59033.103
A27: Cumulative Cash Flow | B27: =B26 -> -120000 | C27: =B27+C26 -> -78000 | D27: =C27+D26 -> -32220 | E27: =D27+E26 -> 17642.4 | F27: =E27+F26 -> 71913.792 | G27: =F27+G26 -> 130946.9
A29: Project NPV (BDT '000) | B29: =NPV($B$12,C26:G26)+B26 -> 57474.026
A30: Project IRR | B30: =IRR(B26:G26) -> 0.28765586
A31: Simple Payback (years, approx.) | B31: =MATCH(TRUE(),INDEX(B27:G27>=0,0),0)-2+IFERROR(-INDEX(B27:G27,MATCH(TRUE(),INDEX(B27:G27>=0,0),0)-1)/INDEX(C26:G26,MATCH(TRUE(),INDEX(B27:G27>=0,0),0)-1),0) -> 2.6461783
A34: Sensitivity: Year 1 EBITDA (BDT '000)
A35: Revenue \ Variable Cost % | B35: VC -15% | C35: VC +0% | D35: VC +15%
A36: Rev -10% | B36: =($B$6*(1+-0.1))-($B$6*(1+-0.1)*$B$8*(1+-0.15))-$B$9 -> 57495 | C36: =($B$6*(1+-0.1))-($B$6*(1+-0.1)*$B$8*(1+0))-$B$9 -> 41700 | D36: =($B$6*(1+-0.1))-($B$6*(1+-0.1)*$B$8*(1+0.15))-$B$9 -> 25905
A37: Rev +0% | B37: =($B$6*(1+0))-($B$6*(1+0)*$B$8*(1+-0.15))-$B$9 -> 65550 | C37: =($B$6*(1+0))-($B$6*(1+0)*$B$8*(1+0))-$B$9 -> 48000 | D37: =($B$6*(1+0))-($B$6*(1+0)*$B$8*(1+0.15))-$B$9 -> 30450
A38: Rev +10% | B38: =($B$6*(1+0.1))-($B$6*(1+0.1)*$B$8*(1+-0.15))-$B$9 -> 73605 | C38: =($B$6*(1+0.1))-($B$6*(1+0.1)*$B$8*(1+0))-$B$9 -> 54300 | D38: =($B$6*(1+0.1))-($B$6*(1+0.1)*$B$8*(1+0.15))-$B$9 -> 34995

Sheet Assumptions_Sources
A1: Assumptions & Data Sources
A3: Purpose | B3: Demonstration workbook built for a Business Planning interview at ACI Premiaflex Plastics Limited. It models the analyses named in the job description (budgeting, MBR dashboards, variance analysis, profitability analysis, feasibility/ROI, and working-capital planning) on a flexible-packaging cost structure.
A4: Company scale & margin benchmark | B4: ACI Limited's consolidated FY2023-24 turnover was BDT 124,315.9 million; the 'Others' segment (which includes Flexible Packaging, alongside Fertilizer and Seed) contributed roughly 25% of group revenue at an estimated ~5% PBT margin. Source: ACI Limited Annual Report FY2023-24 financial-statement analysis (https://www.scribd.com/document/909180738/ACI-FY2023-24-Analysis-Report). Premiaflex itself does not report standalone financials publicly, so the workbook's revenue scale (~BDT 950 million/year) and product/customer mix are illustrative planning assumptions calibrated to a mid-size Bangladeshi flexible packaging converter — not Premiaflex's actual figures.
A5: Product lines | B5: Foil, Film and Paper laminates, matching Premiaflex's stated Flexo CI / Roto-Gravure product scope in the job posting.
A6: Named customers | B6: Unilever, Marico, Emami, Coca-Cola and BAT are the clients named in ACI Premiaflex's own job posting as trusted customers; the revenue-share and margin percentages assigned to each in the Profitability sheet are illustrative assumptions for the demo, not disclosed account data.
A7: Gross margin & cost ratios | B7: Budgeted gross margin of ~32% (COGS ~68% of revenue) and the raw-material/labor/overhead split are typical planning ranges for flexible-packaging converters; flagged as assumptions, not sourced figures.
A8: Working capital targets | B8: DIO 45 / DSO 55 / DPO 40 days reflect typical terms for a converter supplying large multinational FMCG customers (longer receivable cycles, moderate inventory buffers for imported film/foil) — editable blue-font assumption cells on the Working_Capital_CashFlow tab.
A9: New-line feasibility | B9: Capex, revenue ramp, cost and discount-rate assumptions on the Feasibility_NewLine tab are illustrative planning inputs for a hypothetical capacity-expansion decision, structured the way an ROI/NPV case would be built for management.
A10: How to use in the interview | B10: Talk through the model logic (how each tab links to Data_BudgetActual via SUMIFS), not the specific numbers as if they were Premiaflex's real results — be upfront that this is a self-built illustrative model demonstrating the analytical approach, using industry-realistic assumptions.
